qualitative_coding/cli/__init__.py
qualitative_coding/cli/check.py
qualitative_coding/cli/click_aliases.py
qualitative_coding/cli/code.py
qualitative_coding/cli/codebook.py
qualitative_coding/cli/coders.py
qualitative_coding/cli/codes/__init__.py
qualitative_coding/cli/codes/crosstab.py
qualitative_coding/cli/codes/find.py
qualitative_coding/cli/codes/list.py
qualitative_coding/cli/codes/rename.py
qualitative_coding/cli/codes/stats.py
qualitative_coding/cli/corpus/__init__.py
qualitative_coding/cli/corpus/anonymize.py
qualitative_coding/cli/corpus/import_media.py
qualitative_coding/cli/corpus/list.py
qualitative_coding/cli/corpus/move.py
qualitative_coding/cli/corpus/remove.py
qualitative_coding/cli/corpus/update.py
qualitative_coding/cli/decorators.py
qualitative_coding/cli/export.py
qualitative_coding/cli/init.py
qualitative_coding/cli/memo.py
qualitative_coding/cli/options.py
qualitative_coding/cli/upgrade.py
qualitative_coding/cli/version.py
qualitative_coding/codebook.py
qualitative_coding/corpus.py
qualitative_coding/database/errors.py
qualitative_coding/database/models.py
qualitative_coding/demo.qdpx
qualitative_coding/diff.py
qualitative_coding/editors.py
qualitative_coding/exceptions.py
qualitative_coding/helpers.py
qualitative_coding/logs.py
qualitative_coding/media_importers/__init__.py
qualitative_coding/media_importers/base.py
qualitative_coding/media_importers/pandoc.py
qualitative_coding/media_importers/verbatim.py
qualitative_coding/media_importers/vtt.py
qualitative_coding/migrations/__init__.py
qualitative_coding/migrations/migration.py
qualitative_coding/migrations/migration_0_2_3.py
qualitative_coding/migrations/migration_1_0_0.py
qualitative_coding/migrations/migration_1_4_0.py
qualitative_coding/refi_qda/nvivo_project.qdpx
qualitative_coding/refi_qda/reader.py
qualitative_coding/refi_qda/schema.xsd
qualitative_coding/refi_qda/writer.py
qualitative_coding/tests/__init__.py
qualitative_coding/tests/fixtures.py
qualitative_coding-1.7.6.dist-info/LICENSE
qualitative_coding-1.7.6.dist-info/METADATA
qualitative_coding-1.7.6.dist-info/WHEEL
qualitative_coding-1.7.6.dist-info/entry_points.txt
qualitative_coding-1.7.6.dist-info/RECORD
