Metadata-Version: 2.3
Name: qualitative-coding
Version: 1.7.6
Summary: Qualitative coding tools to support computational thinking
License: AGPL3
Author: Chris Proctor
Author-email: chris@chrisproctor.net
Requires-Python: >=3.11,<3.14
Classifier: License :: Other/Proprietary License
Classifier: Programming Language :: Python :: 3
Classifier: Programming Language :: Python :: 3.11
Classifier: Programming Language :: Python :: 3.12
Classifier: Programming Language :: Python :: 3.13
Requires-Dist: click (>=8.1.8,<9.0.0)
Requires-Dist: more-itertools (>=10.6.0,<11.0.0)
Requires-Dist: numpy (>=2.2.1,<3.0.0)
Requires-Dist: pyyaml (>=6.0.2,<7.0.0)
Requires-Dist: rich (>=13.9.4,<14.0.0)
Requires-Dist: semver (>=3.0.2,<4.0.0)
Requires-Dist: spacy (>=3.8.7,<4.0.0)
Requires-Dist: sqlalchemy (>=2.0.37,<3.0.0)
Requires-Dist: structlog (>=25.1.0,<26.0.0)
Requires-Dist: tabulate (>=0.9.0,<0.10.0)
Requires-Dist: tqdm (>=4.67.1,<5.0.0)
Requires-Dist: webvtt-py (>=0.5.1,<0.6.0)
Requires-Dist: xmlschema (>=3.4.3,<4.0.0)
Project-URL: Homepage, https://qualitative-coding.readthedocs.io
Project-URL: Repository, https://github.com/cproctor/qualitative-coding
